{
  "resources": [
    {
      "path": "data.csv",
      "name": "data",
      "profile": "tabular-data-resource",
      "scheme": "file",
      "format": "csv",
      "hashing": "md5",
      "encoding": "utf-8",
      "schema": {
        "fields": [
          {
            "name": "CUST_BREAKDOWN",
            "type": "string",
            "constraints": {
              "enum": [
                "",
                "Custom code 01",
                "Custom code 02"
              ]
            },
            "title": "Custom Breakdown"
          },
          {
            "name": "CUST_BREAKDOWN_LB",
            "type": "string",
            "constraints": {
              "enum": [
                "",
                "Ghorai",
                "Kathmandu"
              ]
            },
            "title": "Label for custom breakdown"
          },
          {
            "name": "REF_AREA",
            "type": "number",
            "constraints": {
              "enum": [
                ""
              ]
            },
            "title": "Reference area"
          },
          {
            "name": "Series",
            "type": "string",
            "constraints": {
              "enum": [
                "",
                "Municipal Solid Waste collection coverage, by cities (%) [11.6.1]"
              ]
            },
            "title": "SDG Series"
          },
          {
            "name": "Units",
            "type": "string",
            "constraints": {
              "enum": [
                "",
                "Percent"
              ]
            },
            "title": "Unit of measure"
          },
          {
            "name": "Value",
            "type": "integer",
            "title": "Value"
          },
          {
            "name": "Year",
            "type": "string",
            "title": "Year"
          }
        ]
      }
    }
  ],
  "profile": "data-package",
  "name": "11-6-1",
  "title": "Proportion of urban solid waste regularly collected and with adequate final discharge out of total urban solid waste generated, by cities"
}