{"data":{"Year":["2000","2005","2010","2015","2016","2000","2005","2010","2015","2016","2000","2005","2010","2015","2016","2000","2005","2010","2015","2016","2000","2005","2010","2015","2016","2000","2005","2010","2015","2016","2000","2005","2010","2015","2016","2000","2005","2010","2015","2016","2000","2005","2010","2015","2016","2000","2005","2010","2015","2016","2000","2005","2010","2015","2016","2000","2005","2010","2015","2016","2000","2005","2010","2015","2016","2000","2005","2010","2015","2016","2000","2005","2010","2015","2016"],"Series":["SH_DTH_NCD","SH_DTH_NCD","SH_DTH_NCD","SH_DTH_NCD","SH_DTH_NCD","SH_DTH_NCD","SH_DTH_NCD","SH_DTH_NCD","SH_DTH_NCD","SH_DTH_NCD","SH_DTH_NCD","SH_DTH_NCD","SH_DTH_NCD","SH_DTH_NCD","SH_DTH_NCD","SH_DTH_NCD","SH_DTH_NCD","SH_DTH_NCD","SH_DTH_NCD","SH_DTH_NCD","SH_DTH_NCD","SH_DTH_NCD","SH_DTH_NCD","SH_DTH_NCD","SH_DTH_NCD","SH_DTH_NCD","SH_DTH_NCD","SH_DTH_NCD","SH_DTH_NCD","SH_DTH_NCD","SH_DTH_NCD","SH_DTH_NCD","SH_DTH_NCD","SH_DTH_NCD","SH_DTH_NCD","SH_DTH_NCD","SH_DTH_NCD","SH_DTH_NCD","SH_DTH_NCD","SH_DTH_NCD","SH_DTH_NCD","SH_DTH_NCD","SH_DTH_NCD","SH_DTH_NCD","SH_DTH_NCD","SH_DTH_NCD","SH_DTH_NCD","SH_DTH_NCD","SH_DTH_NCD","SH_DTH_NCD","SH_DTH_NCD","SH_DTH_NCD","SH_DTH_NCD","SH_DTH_NCD","SH_DTH_NCD","SH_DTH_NCD","SH_DTH_NCD","SH_DTH_NCD","SH_DTH_NCD","SH_DTH_NCD","SH_DTH_NCOM","SH_DTH_NCOM","SH_DTH_NCOM","SH_DTH_NCOM","SH_DTH_NCOM","SH_DTH_NCOM","SH_DTH_NCOM","SH_DTH_NCOM","SH_DTH_NCOM","SH_DTH_NCOM","SH_DTH_NCOM","SH_DTH_NCOM","SH_DTH_NCOM","SH_DTH_NCOM","SH_DTH_NCOM"],"SEX":[null,null,null,null,null,null,null,null,null,null,null,null,null,null,null,null,null,null,null,null,"F","F","F","F","F","F","F","F","F","F","F","F","F","F","F","F","F","F","F","F","M","M","M","M","M","M","M","M","M","M","M","M","M","M","M","M","M","M","M","M",null,null,null,null,null,"F","F","F","F","F","M","M","M","M","M"],"AGE":[null,null,null,null,null,null,null,null,null,null,null,null,null,null,null,null,null,null,null,null,null,null,null,null,null,null,null,null,null,null,null,null,null,null,null,null,null,null,null,null,null,null,null,null,null,null,null,null,null,null,null,null,null,null,null,null,null,null,null,null,"Y30T70","Y30T70","Y30T70","Y30T70","Y30T70","Y30T70","Y30T70","Y30T70","Y30T70","Y30T70","Y30T70","Y30T70","Y30T70","Y30T70","Y30T70"],"COMPOSITE_BREAKDOWN":["NCD_CARDIO","NCD_CARDIO","NCD_CARDIO","NCD_CARDIO","NCD_CARDIO","NCD_CNCR","NCD_CNCR","NCD_CNCR","NCD_CNCR","NCD_CNCR","NCD_CRESPD","NCD_CRESPD","NCD_CRESPD","NCD_CRESPD","NCD_CRESPD","NCD_DIABTS","NCD_DIABTS","NCD_DIABTS","NCD_DIABTS","NCD_DIABTS","NCD_CARDIO","NCD_CARDIO","NCD_CARDIO","NCD_CARDIO","NCD_CARDIO","NCD_CNCR","NCD_CNCR","NCD_CNCR","NCD_CNCR","NCD_CNCR","NCD_CRESPD","NCD_CRESPD","NCD_CRESPD","NCD_CRESPD","NCD_CRESPD","NCD_DIABTS","NCD_DIABTS","NCD_DIABTS","NCD_DIABTS","NCD_DIABTS","NCD_CARDIO","NCD_CARDIO","NCD_CARDIO","NCD_CARDIO","NCD_CARDIO","NCD_CNCR","NCD_CNCR","NCD_CNCR","NCD_CNCR","NCD_CNCR","NCD_CRESPD","NCD_CRESPD","NCD_CRESPD","NCD_CRESPD","NCD_CRESPD","NCD_DIABTS","NCD_DIABTS","NCD_DIABTS","NCD_DIABTS","NCD_DIABTS",null,null,null,null,null,null,null,null,null,null,null,null,null,null,null],"Units":["NUMBER","NUMBER","NUMBER","NUMBER","NUMBER","NUMBER","NUMBER","NUMBER","NUMBER","NUMBER","NUMBER","NUMBER","NUMBER","NUMBER","NUMBER","NUMBER","NUMBER","NUMBER","NUMBER","NUMBER","NUMBER","NUMBER","NUMBER","NUMBER","NUMBER","NUMBER","NUMBER","NUMBER","NUMBER","NUMBER","NUMBER","NUMBER","NUMBER","NUMBER","NUMBER","NUMBER","NUMBER","NUMBER","NUMBER","NUMBER","NUMBER","NUMBER","NUMBER","NUMBER","NUMBER","NUMBER","NUMBER","NUMBER","NUMBER","NUMBER","NUMBER","NUMBER","NUMBER","NUMBER","NUMBER","NUMBER","NUMBER","NUMBER","NUMBER","NUMBER","PT","PT","PT","PT","PT","PT","PT","PT","PT","PT","PT","PT","PT","PT","PT"],"Value":[36775.0,43208.0,47892.0,53981.0,55127.0,11310.0,13128.0,14376.0,16601.0,17049.0,15477.0,16520.0,17302.0,18681.0,18952.0,3270.0,4203.0,5020.0,6285.0,6555.0,15952.0,17803.0,19391.0,22088.0,22577.0,6266.0,7086.0,7568.0,8770.0,8998.0,8433.0,9084.0,9482.0,10262.0,10413.0,1939.0,2514.0,2984.0,3790.0,3964.0,20824.0,25405.0,28502.0,31893.0,32550.0,5044.0,6043.0,6809.0,7831.0,8051.0,7044.0,7437.0,7820.0,8419.0,8539.0,1331.0,1689.0,2037.0,2495.0,2591.0,27.3,25.8,23.8,22.2,21.8,24.2,22.9,21.1,19.6,19.2,30.7,28.7,26.5,25.2,24.8]},"edges":[]}