{"data":{"Year":["2000","2001","2002","2003","2004","2005","2006","2007","2008","2009","2010","2011","2012","2013","2014","2015","2016","2017","2000","2001","2002","2003","2004","2005","2006","2007","2008","2009","2010","2011","2012","2013","2014","2015","2016","2017","2000","2001","2002","2003","2004","2005","2006","2007","2008","2009","2010","2011","2012","2013","2014","2015","2016","2017"],"Series":["SH_H2O_SAFE","SH_H2O_SAFE","SH_H2O_SAFE","SH_H2O_SAFE","SH_H2O_SAFE","SH_H2O_SAFE","SH_H2O_SAFE","SH_H2O_SAFE","SH_H2O_SAFE","SH_H2O_SAFE","SH_H2O_SAFE","SH_H2O_SAFE","SH_H2O_SAFE","SH_H2O_SAFE","SH_H2O_SAFE","SH_H2O_SAFE","SH_H2O_SAFE","SH_H2O_SAFE","SH_H2O_SAFE","SH_H2O_SAFE","SH_H2O_SAFE","SH_H2O_SAFE","SH_H2O_SAFE","SH_H2O_SAFE","SH_H2O_SAFE","SH_H2O_SAFE","SH_H2O_SAFE","SH_H2O_SAFE","SH_H2O_SAFE","SH_H2O_SAFE","SH_H2O_SAFE","SH_H2O_SAFE","SH_H2O_SAFE","SH_H2O_SAFE","SH_H2O_SAFE","SH_H2O_SAFE","SH_H2O_SAFE","SH_H2O_SAFE","SH_H2O_SAFE","SH_H2O_SAFE","SH_H2O_SAFE","SH_H2O_SAFE","SH_H2O_SAFE","SH_H2O_SAFE","SH_H2O_SAFE","SH_H2O_SAFE","SH_H2O_SAFE","SH_H2O_SAFE","SH_H2O_SAFE","SH_H2O_SAFE","SH_H2O_SAFE","SH_H2O_SAFE","SH_H2O_SAFE","SH_H2O_SAFE"],"REF_AREA":[null,null,null,null,null,null,null,null,null,null,null,null,null,null,null,null,null,null,null,null,null,null,null,null,null,null,null,null,null,null,null,null,null,null,null,null,null,null,null,null,null,null,null,null,null,null,null,null,null,null,null,null,null,null],"URBANISATION":[null,null,null,null,null,null,null,null,null,null,null,null,null,null,null,null,null,null,"R","R","R","R","R","R","R","R","R","R","R","R","R","R","R","R","R","R","U","U","U","U","U","U","U","U","U","U","U","U","U","U","U","U","U","U"],"Units":["PT","PT","PT","PT","PT","PT","PT","PT","PT","PT","PT","PT","PT","PT","PT","PT","PT","PT","PT","PT","PT","PT","PT","PT","PT","PT","PT","PT","PT","PT","PT","PT","PT","PT","PT","PT","PT","PT","PT","PT","PT","PT","PT","PT","PT","PT","PT","PT","PT","PT","PT","PT","PT","PT"],"Value":[23.9283,24.16208,24.36175,24.56056,24.7585,24.95553,25.15159,25.34678,25.54093,25.73401,25.92598,26.11691,26.30714,26.49631,26.68465,26.87191,27.0582,27.24335,22.22516,22.42336,22.62156,22.81976,23.01796,23.21616,23.41436,23.61255,23.81075,24.00895,24.20715,24.40535,24.60355,24.80175,24.99995,25.19815,25.39635,25.59455,34.93801,34.88999,34.84197,34.79395,34.74593,34.69791,34.64989,34.60187,34.55385,34.50583,34.45781,34.40979,34.36177,34.31375,34.26573,34.21771,34.16969,34.12167]},"edges":[]}