[{"Year":"2000","Value":0.948,"Units":"Per 100,000 population","Series":"Proportion of the population who are refugees, by country of origin [10.7.4]"},{"Year":"2001","Value":1.232,"Units":"Per 100,000 population","Series":"Proportion of the population who are refugees, by country of origin [10.7.4]"},{"Year":"2002","Value":3.636,"Units":"Per 100,000 population","Series":"Proportion of the population who are refugees, by country of origin [10.7.4]"},{"Year":"2003","Value":4.912,"Units":"Per 100,000 population","Series":"Proportion of the population who are refugees, by country of origin [10.7.4]"},{"Year":"2004","Value":5.562,"Units":"Per 100,000 population","Series":"Proportion of the population who are refugees, by country of origin [10.7.4]"},{"Year":"2005","Value":8.005,"Units":"Per 100,000 population","Series":"Proportion of the population who are refugees, by country of origin [10.7.4]"},{"Year":"2006","Value":10.173,"Units":"Per 100,000 population","Series":"Proportion of the population who are refugees, by country of origin [10.7.4]"},{"Year":"2007","Value":12.757,"Units":"Per 100,000 population","Series":"Proportion of the population who are refugees, by country of origin [10.7.4]"},{"Year":"2008","Value":15.71,"Units":"Per 100,000 population","Series":"Proportion of the population who are refugees, by country of origin [10.7.4]"},{"Year":"2009","Value":18.971,"Units":"Per 100,000 population","Series":"Proportion of the population who are refugees, by country of origin [10.7.4]"},{"Year":"2010","Value":21.773,"Units":"Per 100,000 population","Series":"Proportion of the population who are refugees, by country of origin [10.7.4]"},{"Year":"2011","Value":25.314,"Units":"Per 100,000 population","Series":"Proportion of the population who are refugees, by country of origin [10.7.4]"},{"Year":"2012","Value":28.163,"Units":"Per 100,000 population","Series":"Proportion of the population who are refugees, by country of origin [10.7.4]"},{"Year":"2013","Value":30.084,"Units":"Per 100,000 population","Series":"Proportion of the population who are refugees, by country of origin [10.7.4]"},{"Year":"2014","Value":31.756,"Units":"Per 100,000 population","Series":"Proportion of the population who are refugees, by country of origin [10.7.4]"},{"Year":"2015","Value":33.496,"Units":"Per 100,000 population","Series":"Proportion of the population who are refugees, by country of origin [10.7.4]"},{"Year":"2016","Value":30.673,"Units":"Per 100,000 population","Series":"Proportion of the population who are refugees, by country of origin [10.7.4]"},{"Year":"2017","Value":30.44,"Units":"Per 100,000 population","Series":"Proportion of the population who are refugees, by country of origin [10.7.4]"},{"Year":"2018","Value":30.561,"Units":"Per 100,000 population","Series":"Proportion of the population who are refugees, by country of origin [10.7.4]"},{"Year":"2019","Value":28.071,"Units":"Per 100,000 population","Series":"Proportion of the population who are refugees, by country of origin [10.7.4]"},{"Year":"2020","Value":27.017,"Units":"Per 100,000 population","Series":"Proportion of the population who are refugees, by country of origin [10.7.4]"}]