[{"Year":"2000","Value":7.83,"Units":"MJ_PER_GDP_CON_PPP_USD","Series":"EG_EGY_PRIM"},{"Year":"2001","Value":7.72,"Units":"MJ_PER_GDP_CON_PPP_USD","Series":"EG_EGY_PRIM"},{"Year":"2002","Value":7.79,"Units":"MJ_PER_GDP_CON_PPP_USD","Series":"EG_EGY_PRIM"},{"Year":"2003","Value":7.71,"Units":"MJ_PER_GDP_CON_PPP_USD","Series":"EG_EGY_PRIM"},{"Year":"2004","Value":7.47,"Units":"MJ_PER_GDP_CON_PPP_USD","Series":"EG_EGY_PRIM"},{"Year":"2005","Value":7.47,"Units":"MJ_PER_GDP_CON_PPP_USD","Series":"EG_EGY_PRIM"},{"Year":"2006","Value":7.22,"Units":"MJ_PER_GDP_CON_PPP_USD","Series":"EG_EGY_PRIM"},{"Year":"2007","Value":7.12,"Units":"MJ_PER_GDP_CON_PPP_USD","Series":"EG_EGY_PRIM"},{"Year":"2008","Value":6.94,"Units":"MJ_PER_GDP_CON_PPP_USD","Series":"EG_EGY_PRIM"},{"Year":"2009","Value":6.84,"Units":"MJ_PER_GDP_CON_PPP_USD","Series":"EG_EGY_PRIM"},{"Year":"2010","Value":6.72,"Units":"MJ_PER_GDP_CON_PPP_USD","Series":"EG_EGY_PRIM"},{"Year":"2011","Value":6.72,"Units":"MJ_PER_GDP_CON_PPP_USD","Series":"EG_EGY_PRIM"},{"Year":"2012","Value":6.13,"Units":"MJ_PER_GDP_CON_PPP_USD","Series":"EG_EGY_PRIM"},{"Year":"2013","Value":6.57,"Units":"MJ_PER_GDP_CON_PPP_USD","Series":"EG_EGY_PRIM"},{"Year":"2014","Value":6.45,"Units":"MJ_PER_GDP_CON_PPP_USD","Series":"EG_EGY_PRIM"},{"Year":"2015","Value":6.24,"Units":"MJ_PER_GDP_CON_PPP_USD","Series":"EG_EGY_PRIM"},{"Year":"2016","Value":6.76,"Units":"MJ_PER_GDP_CON_PPP_USD","Series":"EG_EGY_PRIM"},{"Year":"2017","Value":6.61,"Units":"MJ_PER_GDP_CON_PPP_USD","Series":"EG_EGY_PRIM"},{"Year":"2018","Value":6.43,"Units":"MJ_PER_GDP_CON_PPP_USD","Series":"EG_EGY_PRIM"}]