[{"Year":"2010","Value":26834231,"Units":"NUMBER","Series":"SH_TRP_INTVN"},{"Year":"2011","Value":26975315,"Units":"NUMBER","Series":"SH_TRP_INTVN"},{"Year":"2012","Value":20852506,"Units":"NUMBER","Series":"SH_TRP_INTVN"},{"Year":"2013","Value":23979335,"Units":"NUMBER","Series":"SH_TRP_INTVN"},{"Year":"2014","Value":21348508,"Units":"NUMBER","Series":"SH_TRP_INTVN"},{"Year":"2015","Value":18850311,"Units":"NUMBER","Series":"SH_TRP_INTVN"},{"Year":"2016","Value":17552881,"Units":"NUMBER","Series":"SH_TRP_INTVN"},{"Year":"2017","Value":16062081,"Units":"NUMBER","Series":"SH_TRP_INTVN"},{"Year":"2018","Value":14520580,"Units":"NUMBER","Series":"SH_TRP_INTVN"},{"Year":"2019","Value":14118850,"Units":"NUMBER","Series":"SH_TRP_INTVN"}]