{"Year":["2020"],"Series":["Countries that adopt and implement constitutional, statutory and/or policy guarantees for public access to information"],"Reference area":[null],"Sex":["None"],"Age":["None"],"Degree of urbanisation":["None"],"Income or wealth quantile":["None"],"Education level":["None"],"Occupation":["None"],"Custom Breakdown":["None"],"COMPOSITE_BREAKDOWN":["None"],"Disability status":["None"],"Economic activity":["None"],"Type of product":["None"],"Units":["Number"],"Value":[2007]}